wc_client/__init__.py
wc_client/client.py
wc_client/request.py
wc_client-0.2.1.dist-info/METADATA
wc_client-0.2.1.dist-info/WHEEL
wc_client-0.2.1.dist-info/licenses/LICENSE
wc_client-0.2.1.dist-info/RECORD
